<?xml version="1.0" encoding="utf-8" standalone="yes"?>
<Gesture Name="rectangle9" Subject="user05" Number="9" NumPts="538>
   <Point X="194" Y="118" T="1677702606394" />
   <Point X="194" Y="117" T="1677702606411" />
   <Point X="194" Y="116" T="1677702606421" />
   <Point X="194" Y="115" T="1677702606424" />
   <Point X="194" Y="116" T="1677702606481" />
   <Point X="194" Y="117" T="1677702606484" />
   <Point X="194" Y="118" T="1677702606493" />
   <Point X="194" Y="119" T="1677702606496" />
   <Point X="194" Y="120" T="1677702606497" />
   <Point X="194" Y="121" T="1677702606497" />
   <Point X="194" Y="122" T="1677702606497" />
   <Point X="194" Y="123" T="1677702606497" />
   <Point X="194" Y="125" T="1677702606513" />
   <Point X="194" Y="126" T="1677702606513" />
   <Point X="194" Y="127" T="1677702606513" />
   <Point X="194" Y="128" T="1677702606513" />
   <Point X="194" Y="129" T="1677702606529" />
   <Point X="194" Y="130" T="1677702606529" />
   <Point X="194" Y="131" T="1677702606529" />
   <Point X="194" Y="132" T="1677702606544" />
   <Point X="194" Y="133" T="1677702606544" />
   <Point X="194" Y="134" T="1677702606544" />
   <Point X="194" Y="135" T="1677702606560" />
   <Point X="195" Y="136" T="1677702606560" />
   <Point X="195" Y="137" T="1677702606560" />
   <Point X="195" Y="138" T="1677702606560" />
   <Point X="195" Y="139" T="1677702606575" />
   <Point X="196" Y="140" T="1677702606575" />
   <Point X="196" Y="141" T="1677702606575" />
   <Point X="196" Y="142" T="1677702606575" />
   <Point X="196" Y="143" T="1677702606591" />
   <Point X="196" Y="144" T="1677702606591" />
   <Point X="196" Y="145" T="1677702606591" />
   <Point X="196" Y="146" T="1677702606591" />
   <Point X="196" Y="147" T="1677702606607" />
   <Point X="196" Y="148" T="1677702606607" />
   <Point X="196" Y="149" T="1677702606607" />
   <Point X="196" Y="150" T="1677702606607" />
   <Point X="196" Y="151" T="1677702606622" />
   <Point X="196" Y="152" T="1677702606622" />
   <Point X="196" Y="153" T="1677702606622" />
   <Point X="196" Y="154" T="1677702606622" />
   <Point X="196" Y="155" T="1677702606638" />
   <Point X="196" Y="156" T="1677702606638" />
   <Point X="196" Y="157" T="1677702606649" />
   <Point X="196" Y="158" T="1677702606652" />
   <Point X="196" Y="159" T="1677702606656" />
   <Point X="196" Y="160" T="1677702606660" />
   <Point X="196" Y="161" T="1677702606666" />
   <Point X="196" Y="162" T="1677702606668" />
   <Point X="196" Y="164" T="1677702606672" />
   <Point X="196" Y="165" T="1677702606676" />
   <Point X="196" Y="166" T="1677702606680" />
   <Point X="195" Y="167" T="1677702606681" />
   <Point X="195" Y="168" T="1677702606681" />
   <Point X="195" Y="169" T="1677702606681" />
   <Point X="195" Y="171" T="1677702606681" />
   <Point X="195" Y="172" T="1677702606697" />
   <Point X="195" Y="173" T="1677702606697" />
   <Point X="195" Y="174" T="1677702606697" />
   <Point X="195" Y="175" T="1677702606697" />
   <Point X="195" Y="177" T="1677702606712" />
   <Point X="195" Y="178" T="1677702606712" />
   <Point X="194" Y="179" T="1677702606712" />
   <Point X="194" Y="180" T="1677702606728" />
   <Point X="194" Y="182" T="1677702606728" />
   <Point X="194" Y="183" T="1677702606728" />
   <Point X="194" Y="184" T="1677702606728" />
   <Point X="194" Y="185" T="1677702606743" />
   <Point X="194" Y="186" T="1677702606743" />
   <Point X="194" Y="187" T="1677702606743" />
   <Point X="194" Y="188" T="1677702606743" />
   <Point X="194" Y="189" T="1677702606759" />
   <Point X="194" Y="190" T="1677702606759" />
   <Point X="194" Y="191" T="1677702606759" />
   <Point X="194" Y="192" T="1677702606759" />
   <Point X="194" Y="193" T="1677702606775" />
   <Point X="194" Y="194" T="1677702606775" />
   <Point X="193" Y="195" T="1677702606775" />
   <Point X="193" Y="196" T="1677702606791" />
   <Point X="193" Y="197" T="1677702606791" />
   <Point X="193" Y="198" T="1677702606791" />
   <Point X="193" Y="199" T="1677702606791" />
   <Point X="193" Y="200" T="1677702606806" />
   <Point X="193" Y="201" T="1677702606806" />
   <Point X="193" Y="202" T="1677702606806" />
   <Point X="192" Y="203" T="1677702606806" />
   <Point X="192" Y="204" T="1677702606822" />
   <Point X="192" Y="205" T="1677702606832" />
   <Point X="192" Y="206" T="1677702606836" />
   <Point X="192" Y="207" T="1677702606840" />
   <Point X="192" Y="208" T="1677702606844" />
   <Point X="191" Y="209" T="1677702606848" />
   <Point X="191" Y="210" T="1677702606852" />
   <Point X="191" Y="211" T="1677702606856" />
   <Point X="191" Y="212" T="1677702606860" />
   <Point X="191" Y="213" T="1677702606865" />
   <Point X="190" Y="214" T="1677702606865" />
   <Point X="190" Y="215" T="1677702606865" />
   <Point X="190" Y="216" T="1677702606865" />
   <Point X="190" Y="217" T="1677702606880" />
   <Point X="190" Y="218" T="1677702606880" />
   <Point X="189" Y="218" T="1677702606880" />
   <Point X="189" Y="219" T="1677702606880" />
   <Point X="189" Y="220" T="1677702606896" />
   <Point X="189" Y="221" T="1677702606896" />
   <Point X="189" Y="222" T="1677702606896" />
   <Point X="188" Y="222" T="1677702606912" />
   <Point X="188" Y="223" T="1677702606912" />
   <Point X="188" Y="224" T="1677702606927" />
   <Point X="189" Y="224" T="1677702606974" />
   <Point X="190" Y="224" T="1677702606974" />
   <Point X="191" Y="224" T="1677702606990" />
   <Point X="192" Y="224" T="1677702607004" />
   <Point X="193" Y="223" T="1677702607009" />
   <Point X="194" Y="223" T="1677702607016" />
   <Point X="195" Y="223" T="1677702607020" />
   <Point X="196" Y="223" T="1677702607024" />
   <Point X="197" Y="222" T="1677702607027" />
   <Point X="198" Y="222" T="1677702607031" />
   <Point X="199" Y="222" T="1677702607031" />
   <Point X="200" Y="222" T="1677702607031" />
   <Point X="201" Y="221" T="1677702607031" />
   <Point X="202" Y="221" T="1677702607049" />
   <Point X="203" Y="221" T="1677702607052" />
   <Point X="204" Y="221" T="1677702607056" />
   <Point X="205" Y="221" T="1677702607060" />
   <Point X="206" Y="220" T="1677702607064" />
   <Point X="207" Y="220" T="1677702607065" />
   <Point X="208" Y="220" T="1677702607065" />
   <Point X="209" Y="220" T="1677702607065" />
   <Point X="210" Y="220" T="1677702607065" />
   <Point X="211" Y="220" T="1677702607081" />
   <Point X="212" Y="219" T="1677702607081" />
   <Point X="213" Y="219" T="1677702607081" />
   <Point X="214" Y="219" T="1677702607081" />
   <Point X="215" Y="219" T="1677702607097" />
   <Point X="216" Y="219" T="1677702607097" />
   <Point X="217" Y="219" T="1677702607097" />
   <Point X="218" Y="219" T="1677702607112" />
   <Point X="219" Y="219" T="1677702607112" />
   <Point X="220" Y="219" T="1677702607112" />
   <Point X="221" Y="219" T="1677702607128" />
   <Point X="222" Y="219" T="1677702607128" />
   <Point X="223" Y="219" T="1677702607128" />
   <Point X="224" Y="219" T="1677702607128" />
   <Point X="225" Y="219" T="1677702607143" />
   <Point X="226" Y="219" T="1677702607143" />
   <Point X="227" Y="219" T="1677702607143" />
   <Point X="228" Y="219" T="1677702607159" />
   <Point X="229" Y="219" T="1677702607159" />
   <Point X="230" Y="219" T="1677702607159" />
   <Point X="231" Y="219" T="1677702607175" />
   <Point X="232" Y="219" T="1677702607175" />
   <Point X="233" Y="219" T="1677702607184" />
   <Point X="234" Y="219" T="1677702607188" />
   <Point X="235" Y="219" T="1677702607192" />
   <Point X="236" Y="219" T="1677702607196" />
   <Point X="237" Y="219" T="1677702607199" />
   <Point X="238" Y="219" T="1677702607204" />
   <Point X="239" Y="219" T="1677702607208" />
   <Point X="240" Y="219" T="1677702607212" />
   <Point X="241" Y="219" T="1677702607214" />
   <Point X="242" Y="219" T="1677702607214" />
   <Point X="243" Y="219" T="1677702607214" />
   <Point X="244" Y="219" T="1677702607214" />
   <Point X="245" Y="219" T="1677702607230" />
   <Point X="246" Y="219" T="1677702607230" />
   <Point X="247" Y="219" T="1677702607230" />
   <Point X="248" Y="219" T="1677702607230" />
   <Point X="249" Y="219" T="1677702607245" />
   <Point X="250" Y="219" T="1677702607245" />
   <Point X="251" Y="219" T="1677702607245" />
   <Point X="252" Y="219" T="1677702607245" />
   <Point X="253" Y="219" T="1677702607261" />
   <Point X="254" Y="219" T="1677702607261" />
   <Point X="255" Y="219" T="1677702607261" />
   <Point X="256" Y="219" T="1677702607276" />
   <Point X="257" Y="219" T="1677702607276" />
   <Point X="258" Y="219" T="1677702607276" />
   <Point X="259" Y="219" T="1677702607276" />
   <Point X="261" Y="219" T="1677702607292" />
   <Point X="262" Y="219" T="1677702607292" />
   <Point X="263" Y="219" T="1677702607292" />
   <Point X="264" Y="219" T="1677702607308" />
   <Point X="265" Y="219" T="1677702607308" />
   <Point X="266" Y="219" T="1677702607308" />
   <Point X="267" Y="219" T="1677702607323" />
   <Point X="268" Y="220" T="1677702607323" />
   <Point X="269" Y="220" T="1677702607323" />
   <Point X="271" Y="220" T="1677702607323" />
   <Point X="272" Y="220" T="1677702607339" />
   <Point X="273" Y="220" T="1677702607339" />
   <Point X="274" Y="220" T="1677702607348" />
   <Point X="275" Y="220" T="1677702607353" />
   <Point X="276" Y="220" T="1677702607356" />
   <Point X="277" Y="221" T="1677702607360" />
   <Point X="278" Y="221" T="1677702607366" />
   <Point X="279" Y="221" T="1677702607368" />
   <Point X="280" Y="221" T="1677702607371" />
   <Point X="281" Y="221" T="1677702607376" />
   <Point X="282" Y="221" T="1677702607380" />
   <Point X="283" Y="221" T="1677702607381" />
   <Point X="284" Y="221" T="1677702607381" />
   <Point X="285" Y="221" T="1677702607381" />
   <Point X="286" Y="221" T="1677702607397" />
   <Point X="287" Y="222" T="1677702607397" />
   <Point X="288" Y="222" T="1677702607397" />
   <Point X="289" Y="222" T="1677702607397" />
   <Point X="290" Y="222" T="1677702607412" />
   <Point X="291" Y="222" T="1677702607412" />
   <Point X="292" Y="222" T="1677702607412" />
   <Point X="293" Y="222" T="1677702607428" />
   <Point X="294" Y="223" T="1677702607428" />
   <Point X="295" Y="223" T="1677702607428" />
   <Point X="296" Y="223" T="1677702607428" />
   <Point X="297" Y="223" T="1677702607443" />
   <Point X="298" Y="223" T="1677702607443" />
   <Point X="299" Y="223" T="1677702607443" />
   <Point X="300" Y="224" T="1677702607459" />
   <Point X="301" Y="224" T="1677702607459" />
   <Point X="302" Y="224" T="1677702607459" />
   <Point X="303" Y="224" T="1677702607459" />
   <Point X="304" Y="224" T="1677702607475" />
   <Point X="305" Y="224" T="1677702607475" />
   <Point X="306" Y="224" T="1677702607475" />
   <Point X="307" Y="224" T="1677702607490" />
   <Point X="308" Y="224" T="1677702607490" />
   <Point X="309" Y="224" T="1677702607490" />
   <Point X="311" Y="225" T="1677702607490" />
   <Point X="312" Y="225" T="1677702607506" />
   <Point X="313" Y="225" T="1677702607506" />
   <Point X="314" Y="225" T="1677702607506" />
   <Point X="315" Y="225" T="1677702607506" />
   <Point X="316" Y="225" T="1677702607522" />
   <Point X="318" Y="225" T="1677702607522" />
   <Point X="319" Y="225" T="1677702607532" />
   <Point X="320" Y="225" T="1677702607536" />
   <Point X="321" Y="225" T="1677702607541" />
   <Point X="323" Y="225" T="1677702607543" />
   <Point X="324" Y="225" T="1677702607549" />
   <Point X="325" Y="225" T="1677702607553" />
   <Point X="327" Y="225" T="1677702607556" />
   <Point X="328" Y="225" T="1677702607560" />
   <Point X="329" Y="225" T="1677702607565" />
   <Point X="330" Y="225" T="1677702607565" />
   <Point X="331" Y="225" T="1677702607565" />
   <Point X="332" Y="225" T="1677702607565" />
   <Point X="333" Y="225" T="1677702607580" />
   <Point X="334" Y="225" T="1677702607580" />
   <Point X="335" Y="225" T="1677702607580" />
   <Point X="336" Y="225" T="1677702607580" />
   <Point X="337" Y="225" T="1677702607596" />
   <Point X="338" Y="225" T="1677702607596" />
   <Point X="339" Y="225" T="1677702607596" />
   <Point X="340" Y="225" T="1677702607612" />
   <Point X="341" Y="225" T="1677702607612" />
   <Point X="342" Y="225" T="1677702607612" />
   <Point X="343" Y="225" T="1677702607627" />
   <Point X="343" Y="226" T="1677702607627" />
   <Point X="344" Y="226" T="1677702607627" />
   <Point X="345" Y="226" T="1677702607643" />
   <Point X="346" Y="226" T="1677702607643" />
   <Point X="347" Y="226" T="1677702607659" />
   <Point X="347" Y="227" T="1677702607659" />
   <Point X="348" Y="227" T="1677702607659" />
   <Point X="349" Y="227" T="1677702607674" />
   <Point X="350" Y="227" T="1677702607699" />
   <Point X="350" Y="226" T="1677702607747" />
   <Point X="350" Y="224" T="1677702607762" />
   <Point X="350" Y="223" T="1677702607762" />
   <Point X="350" Y="222" T="1677702607778" />
   <Point X="350" Y="221" T="1677702607778" />
   <Point X="350" Y="220" T="1677702607794" />
   <Point X="350" Y="219" T="1677702607794" />
   <Point X="350" Y="218" T="1677702607794" />
   <Point X="350" Y="217" T="1677702607794" />
   <Point X="350" Y="216" T="1677702607809" />
   <Point X="350" Y="215" T="1677702607809" />
   <Point X="350" Y="214" T="1677702607809" />
   <Point X="350" Y="213" T="1677702607809" />
   <Point X="350" Y="212" T="1677702607825" />
   <Point X="350" Y="210" T="1677702607825" />
   <Point X="350" Y="209" T="1677702607825" />
   <Point X="350" Y="208" T="1677702607840" />
   <Point X="350" Y="207" T="1677702607840" />
   <Point X="350" Y="205" T="1677702607840" />
   <Point X="350" Y="204" T="1677702607840" />
   <Point X="350" Y="203" T="1677702607856" />
   <Point X="350" Y="202" T="1677702607856" />
   <Point X="350" Y="201" T="1677702607856" />
   <Point X="350" Y="200" T="1677702607856" />
   <Point X="350" Y="198" T="1677702607871" />
   <Point X="350" Y="197" T="1677702607871" />
   <Point X="350" Y="196" T="1677702607880" />
   <Point X="350" Y="195" T="1677702607885" />
   <Point X="350" Y="194" T="1677702607888" />
   <Point X="350" Y="193" T="1677702607892" />
   <Point X="350" Y="192" T="1677702607896" />
   <Point X="350" Y="191" T="1677702607900" />
   <Point X="350" Y="190" T="1677702607904" />
   <Point X="350" Y="189" T="1677702607908" />
   <Point X="350" Y="188" T="1677702607912" />
   <Point X="351" Y="187" T="1677702607914" />
   <Point X="351" Y="186" T="1677702607914" />
   <Point X="351" Y="185" T="1677702607914" />
   <Point X="351" Y="184" T="1677702607914" />
   <Point X="351" Y="182" T="1677702607930" />
   <Point X="351" Y="181" T="1677702607930" />
   <Point X="352" Y="180" T="1677702607930" />
   <Point X="352" Y="179" T="1677702607930" />
   <Point X="352" Y="177" T="1677702607945" />
   <Point X="352" Y="176" T="1677702607945" />
   <Point X="352" Y="175" T="1677702607945" />
   <Point X="352" Y="174" T="1677702607945" />
   <Point X="352" Y="172" T="1677702607961" />
   <Point X="352" Y="171" T="1677702607961" />
   <Point X="352" Y="170" T="1677702607961" />
   <Point X="352" Y="169" T="1677702607961" />
   <Point X="352" Y="167" T="1677702607976" />
   <Point X="352" Y="166" T="1677702607976" />
   <Point X="352" Y="165" T="1677702607976" />
   <Point X="352" Y="164" T="1677702607992" />
   <Point X="352" Y="163" T="1677702607992" />
   <Point X="352" Y="162" T="1677702607992" />
   <Point X="352" Y="161" T="1677702607992" />
   <Point X="352" Y="160" T="1677702608008" />
   <Point X="352" Y="159" T="1677702608008" />
   <Point X="352" Y="158" T="1677702608008" />
   <Point X="352" Y="157" T="1677702608008" />
   <Point X="352" Y="156" T="1677702608023" />
   <Point X="352" Y="155" T="1677702608023" />
   <Point X="352" Y="154" T="1677702608023" />
   <Point X="352" Y="153" T="1677702608023" />
   <Point X="352" Y="152" T="1677702608039" />
   <Point X="352" Y="151" T="1677702608039" />
   <Point X="352" Y="150" T="1677702608049" />
   <Point X="352" Y="149" T="1677702608052" />
   <Point X="352" Y="148" T="1677702608056" />
   <Point X="352" Y="147" T="1677702608060" />
   <Point X="351" Y="145" T="1677702608065" />
   <Point X="351" Y="144" T="1677702608068" />
   <Point X="351" Y="143" T="1677702608072" />
   <Point X="351" Y="142" T="1677702608076" />
   <Point X="351" Y="141" T="1677702608080" />
   <Point X="351" Y="140" T="1677702608080" />
   <Point X="351" Y="138" T="1677702608080" />
   <Point X="351" Y="137" T="1677702608080" />
   <Point X="351" Y="136" T="1677702608080" />
   <Point X="351" Y="135" T="1677702608096" />
   <Point X="351" Y="134" T="1677702608096" />
   <Point X="351" Y="133" T="1677702608096" />
   <Point X="351" Y="132" T="1677702608112" />
   <Point X="351" Y="131" T="1677702608112" />
   <Point X="352" Y="130" T="1677702608112" />
   <Point X="352" Y="129" T="1677702608112" />
   <Point X="352" Y="128" T="1677702608127" />
   <Point X="352" Y="127" T="1677702608127" />
   <Point X="352" Y="126" T="1677702608127" />
   <Point X="352" Y="125" T="1677702608127" />
   <Point X="352" Y="124" T="1677702608143" />
   <Point X="352" Y="123" T="1677702608143" />
   <Point X="352" Y="122" T="1677702608143" />
   <Point X="352" Y="121" T="1677702608143" />
   <Point X="352" Y="120" T="1677702608158" />
   <Point X="352" Y="119" T="1677702608158" />
   <Point X="352" Y="118" T="1677702608158" />
   <Point X="352" Y="117" T="1677702608158" />
   <Point X="352" Y="116" T="1677702608174" />
   <Point X="352" Y="115" T="1677702608174" />
   <Point X="352" Y="114" T="1677702608174" />
   <Point X="352" Y="113" T="1677702608190" />
   <Point X="352" Y="112" T="1677702608190" />
   <Point X="352" Y="111" T="1677702608205" />
   <Point X="352" Y="110" T="1677702608205" />
   <Point X="352" Y="109" T="1677702608221" />
   <Point X="353" Y="109" T="1677702608233" />
   <Point X="353" Y="108" T="1677702608235" />
   <Point X="354" Y="108" T="1677702608245" />
   <Point X="354" Y="107" T="1677702608248" />
   <Point X="355" Y="106" T="1677702608252" />
   <Point X="356" Y="105" T="1677702608261" />
   <Point X="357" Y="104" T="1677702608264" />
   <Point X="357" Y="103" T="1677702608264" />
   <Point X="358" Y="102" T="1677702608280" />
   <Point X="358" Y="101" T="1677702608280" />
   <Point X="359" Y="101" T="1677702608280" />
   <Point X="359" Y="100" T="1677702608295" />
   <Point X="359" Y="99" T="1677702608295" />
   <Point X="359" Y="98" T="1677702608319" />
   <Point X="359" Y="97" T="1677702608325" />
   <Point X="358" Y="97" T="1677702608372" />
   <Point X="357" Y="97" T="1677702608388" />
   <Point X="356" Y="97" T="1677702608400" />
   <Point X="355" Y="97" T="1677702608408" />
   <Point X="354" Y="97" T="1677702608416" />
   <Point X="353" Y="97" T="1677702608424" />
   <Point X="352" Y="97" T="1677702608428" />
   <Point X="351" Y="97" T="1677702608431" />
   <Point X="350" Y="97" T="1677702608431" />
   <Point X="349" Y="97" T="1677702608431" />
   <Point X="348" Y="98" T="1677702608446" />
   <Point X="347" Y="98" T="1677702608446" />
   <Point X="346" Y="98" T="1677702608446" />
   <Point X="345" Y="98" T="1677702608462" />
   <Point X="344" Y="98" T="1677702608462" />
   <Point X="343" Y="99" T="1677702608462" />
   <Point X="342" Y="99" T="1677702608462" />
   <Point X="341" Y="99" T="1677702608478" />
   <Point X="340" Y="99" T="1677702608478" />
   <Point X="338" Y="99" T="1677702608478" />
   <Point X="337" Y="99" T="1677702608478" />
   <Point X="336" Y="100" T="1677702608493" />
   <Point X="335" Y="100" T="1677702608500" />
   <Point X="334" Y="100" T="1677702608504" />
   <Point X="333" Y="100" T="1677702608508" />
   <Point X="331" Y="100" T="1677702608512" />
   <Point X="330" Y="100" T="1677702608515" />
   <Point X="329" Y="100" T="1677702608515" />
   <Point X="328" Y="100" T="1677702608515" />
   <Point X="326" Y="100" T="1677702608515" />
   <Point X="325" Y="100" T="1677702608531" />
   <Point X="324" Y="100" T="1677702608531" />
   <Point X="322" Y="100" T="1677702608531" />
   <Point X="321" Y="100" T="1677702608531" />
   <Point X="320" Y="100" T="1677702608546" />
   <Point X="318" Y="100" T="1677702608546" />
   <Point X="317" Y="100" T="1677702608546" />
   <Point X="316" Y="100" T="1677702608546" />
   <Point X="314" Y="100" T="1677702608562" />
   <Point X="313" Y="100" T="1677702608562" />
   <Point X="312" Y="100" T="1677702608562" />
   <Point X="311" Y="100" T="1677702608562" />
   <Point X="310" Y="100" T="1677702608580" />
   <Point X="308" Y="100" T="1677702608584" />
   <Point X="307" Y="100" T="1677702608588" />
   <Point X="306" Y="100" T="1677702608592" />
   <Point X="305" Y="100" T="1677702608596" />
   <Point X="303" Y="100" T="1677702608601" />
   <Point X="302" Y="100" T="1677702608604" />
   <Point X="301" Y="100" T="1677702608608" />
   <Point X="300" Y="100" T="1677702608612" />
   <Point X="299" Y="100" T="1677702608614" />
   <Point X="297" Y="100" T="1677702608614" />
   <Point X="296" Y="99" T="1677702608614" />
   <Point X="295" Y="99" T="1677702608628" />
   <Point X="294" Y="99" T="1677702608632" />
   <Point X="293" Y="99" T="1677702608636" />
   <Point X="292" Y="99" T="1677702608640" />
   <Point X="290" Y="99" T="1677702608641" />
   <Point X="289" Y="99" T="1677702608641" />
   <Point X="288" Y="99" T="1677702608641" />
   <Point X="287" Y="99" T="1677702608641" />
   <Point X="286" Y="99" T="1677702608657" />
   <Point X="285" Y="99" T="1677702608657" />
   <Point X="283" Y="99" T="1677702608657" />
   <Point X="282" Y="99" T="1677702608657" />
   <Point X="281" Y="98" T="1677702608673" />
   <Point X="280" Y="98" T="1677702608673" />
   <Point X="278" Y="98" T="1677702608673" />
   <Point X="277" Y="98" T="1677702608673" />
   <Point X="276" Y="98" T="1677702608688" />
   <Point X="275" Y="98" T="1677702608688" />
   <Point X="273" Y="98" T="1677702608688" />
   <Point X="272" Y="98" T="1677702608688" />
   <Point X="271" Y="98" T="1677702608704" />
   <Point X="270" Y="98" T="1677702608704" />
   <Point X="269" Y="98" T="1677702608704" />
   <Point X="267" Y="98" T="1677702608720" />
   <Point X="266" Y="98" T="1677702608720" />
   <Point X="265" Y="98" T="1677702608720" />
   <Point X="264" Y="98" T="1677702608720" />
   <Point X="263" Y="98" T="1677702608735" />
   <Point X="262" Y="98" T="1677702608735" />
   <Point X="261" Y="98" T="1677702608748" />
   <Point X="260" Y="98" T="1677702608752" />
   <Point X="259" Y="98" T="1677702608757" />
   <Point X="258" Y="98" T="1677702608759" />
   <Point X="257" Y="98" T="1677702608764" />
   <Point X="256" Y="98" T="1677702608773" />
   <Point X="255" Y="98" T="1677702608776" />
   <Point X="254" Y="98" T="1677702608780" />
   <Point X="253" Y="98" T="1677702608780" />
   <Point X="252" Y="98" T="1677702608796" />
   <Point X="251" Y="98" T="1677702608796" />
   <Point X="250" Y="98" T="1677702608812" />
   <Point X="249" Y="98" T="1677702608812" />
   <Point X="249" Y="97" T="1677702608812" />
   <Point X="248" Y="97" T="1677702608812" />
   <Point X="247" Y="97" T="1677702608827" />
   <Point X="246" Y="97" T="1677702608827" />
   <Point X="245" Y="97" T="1677702608843" />
   <Point X="244" Y="97" T="1677702608843" />
   <Point X="243" Y="97" T="1677702608859" />
   <Point X="242" Y="97" T="1677702608859" />
   <Point X="241" Y="97" T="1677702608874" />
   <Point X="240" Y="97" T="1677702608874" />
   <Point X="239" Y="97" T="1677702608890" />
   <Point X="238" Y="97" T="1677702608890" />
   <Point X="237" Y="97" T="1677702608890" />
   <Point X="236" Y="97" T="1677702608905" />
   <Point X="235" Y="97" T="1677702608905" />
   <Point X="234" Y="97" T="1677702608921" />
   <Point X="233" Y="98" T="1677702608933" />
   <Point X="232" Y="98" T="1677702608935" />
   <Point X="231" Y="98" T="1677702608945" />
   <Point X="230" Y="98" T="1677702608948" />
   <Point X="229" Y="98" T="1677702608952" />
   <Point X="228" Y="99" T="1677702608961" />
   <Point X="227" Y="99" T="1677702608964" />
   <Point X="226" Y="99" T="1677702608964" />
   <Point X="225" Y="99" T="1677702608964" />
   <Point X="224" Y="99" T="1677702608964" />
   <Point X="223" Y="99" T="1677702608979" />
   <Point X="222" Y="99" T="1677702608979" />
   <Point X="221" Y="99" T="1677702608979" />
   <Point X="220" Y="99" T="1677702608979" />
   <Point X="219" Y="99" T="1677702608995" />
   <Point X="218" Y="99" T="1677702608995" />
   <Point X="217" Y="99" T="1677702608995" />
   <Point X="216" Y="99" T="1677702608995" />
   <Point X="215" Y="99" T="1677702609011" />
   <Point X="214" Y="99" T="1677702609011" />
   <Point X="213" Y="99" T="1677702609011" />
   <Point X="212" Y="99" T="1677702609011" />
   <Point X="211" Y="99" T="1677702609026" />
   <Point X="210" Y="99" T="1677702609026" />
   <Point X="209" Y="99" T="1677702609026" />
   <Point X="208" Y="99" T="1677702609026" />
   <Point X="207" Y="99" T="1677702609042" />
   <Point X="206" Y="99" T="1677702609042" />
   <Point X="205" Y="99" T="1677702609042" />
   <Point X="204" Y="99" T="1677702609042" />
   <Point X="203" Y="99" T="1677702609058" />
   <Point X="202" Y="99" T="1677702609068" />
   <Point X="201" Y="99" T="1677702609072" />
   <Point X="200" Y="99" T="1677702609076" />
   <Point X="199" Y="99" T="1677702609081" />
</Gesture>