<?xml version="1.0" encoding="utf-8" standalone="yes"?>
<Gesture Name="rectangle08" Subject="user02" Number="8" NumPts="369">
<Point X="134" Y="54" T="2" />
<Point X="134" Y="53" T="3" />
<Point X="134" Y="52" T="4" />
<Point X="133" Y="52" T="5" />
<Point X="134" Y="53" T="6" />
<Point X="134" Y="54" T="7" />
<Point X="134" Y="55" T="8" />
<Point X="134" Y="56" T="9" />
<Point X="134" Y="57" T="10" />
<Point X="134" Y="58" T="11" />
<Point X="134" Y="60" T="12" />
<Point X="135" Y="62" T="13" />
<Point X="135" Y="64" T="14" />
<Point X="135" Y="67" T="15" />
<Point X="135" Y="71" T="16" />
<Point X="136" Y="75" T="17" />
<Point X="136" Y="79" T="18" />
<Point X="136" Y="84" T="19" />
<Point X="136" Y="89" T="20" />
<Point X="137" Y="95" T="21" />
<Point X="137" Y="100" T="22" />
<Point X="138" Y="105" T="23" />
<Point X="138" Y="111" T="24" />
<Point X="139" Y="115" T="25" />
<Point X="139" Y="120" T="26" />
<Point X="140" Y="124" T="27" />
<Point X="140" Y="128" T="28" />
<Point X="140" Y="132" T="29" />
<Point X="141" Y="135" T="30" />
<Point X="141" Y="138" T="31" />
<Point X="141" Y="141" T="32" />
<Point X="141" Y="143" T="33" />
<Point X="141" Y="145" T="34" />
<Point X="139" Y="148" T="35" />
<Point X="139" Y="150" T="36" />
<Point X="138" Y="152" T="37" />
<Point X="138" Y="154" T="38" />
<Point X="137" Y="156" T="39" />
<Point X="136" Y="157" T="40" />
<Point X="136" Y="159" T="41" />
<Point X="135" Y="160" T="42" />
<Point X="134" Y="161" T="43" />
<Point X="134" Y="163" T="44" />
<Point X="134" Y="164" T="45" />
<Point X="134" Y="165" T="46" />
<Point X="134" Y="166" T="47" />
<Point X="134" Y="167" T="48" />
<Point X="134" Y="168" T="49" />
<Point X="135" Y="168" T="50" />
<Point X="136" Y="168" T="51" />
<Point X="137" Y="168" T="52" />
<Point X="138" Y="168" T="53" />
<Point X="138" Y="167" T="54" />
<Point X="139" Y="167" T="55" />
<Point X="140" Y="167" T="56" />
<Point X="141" Y="167" T="57" />
<Point X="143" Y="166" T="58" />
<Point X="144" Y="166" T="59" />
<Point X="145" Y="166" T="60" />
<Point X="147" Y="166" T="61" />
<Point X="149" Y="165" T="62" />
<Point X="150" Y="165" T="63" />
<Point X="153" Y="165" T="64" />
<Point X="155" Y="165" T="65" />
<Point X="158" Y="165" T="66" />
<Point X="161" Y="165" T="67" />
<Point X="165" Y="165" T="68" />
<Point X="168" Y="164" T="69" />
<Point X="172" Y="164" T="70" />
<Point X="177" Y="164" T="71" />
<Point X="181" Y="164" T="72" />
<Point X="186" Y="164" T="73" />
<Point X="191" Y="164" T="74" />
<Point X="196" Y="164" T="75" />
<Point X="201" Y="164" T="76" />
<Point X="206" Y="164" T="77" />
<Point X="212" Y="164" T="78" />
<Point X="217" Y="163" T="79" />
<Point X="222" Y="163" T="80" />
<Point X="228" Y="163" T="81" />
<Point X="234" Y="162" T="82" />
<Point X="239" Y="161" T="83" />
<Point X="245" Y="161" T="84" />
<Point X="250" Y="160" T="85" />
<Point X="256" Y="159" T="86" />
<Point X="262" Y="158" T="87" />
<Point X="267" Y="158" T="88" />
<Point X="273" Y="157" T="89" />
<Point X="278" Y="157" T="90" />
<Point X="283" Y="157" T="91" />
<Point X="288" Y="157" T="92" />
<Point X="293" Y="157" T="93" />
<Point X="298" Y="157" T="94" />
<Point X="302" Y="157" T="95" />
<Point X="306" Y="158" T="96" />
<Point X="310" Y="158" T="97" />
<Point X="314" Y="159" T="98" />
<Point X="319" Y="159" T="99" />
<Point X="323" Y="160" T="100" />
<Point X="327" Y="160" T="101" />
<Point X="331" Y="161" T="102" />
<Point X="334" Y="161" T="103" />
<Point X="338" Y="161" T="104" />
<Point X="341" Y="161" T="105" />
<Point X="345" Y="161" T="106" />
<Point X="348" Y="162" T="107" />
<Point X="351" Y="162" T="108" />
<Point X="354" Y="162" T="109" />
<Point X="357" Y="162" T="110" />
<Point X="360" Y="162" T="111" />
<Point X="363" Y="162" T="112" />
<Point X="366" Y="162" T="113" />
<Point X="369" Y="161" T="114" />
<Point X="372" Y="161" T="115" />
<Point X="375" Y="161" T="116" />
<Point X="378" Y="160" T="117" />
<Point X="381" Y="160" T="118" />
<Point X="384" Y="160" T="119" />
<Point X="387" Y="160" T="120" />
<Point X="391" Y="160" T="121" />
<Point X="394" Y="160" T="122" />
<Point X="397" Y="160" T="123" />
<Point X="400" Y="160" T="124" />
<Point X="403" Y="161" T="125" />
<Point X="406" Y="161" T="126" />
<Point X="409" Y="162" T="127" />
<Point X="412" Y="162" T="128" />
<Point X="415" Y="163" T="129" />
<Point X="417" Y="163" T="130" />
<Point X="420" Y="163" T="131" />
<Point X="422" Y="164" T="132" />
<Point X="424" Y="164" T="133" />
<Point X="426" Y="165" T="134" />
<Point X="428" Y="165" T="135" />
<Point X="429" Y="165" T="136" />
<Point X="431" Y="165" T="137" />
<Point X="432" Y="165" T="138" />
<Point X="434" Y="165" T="139" />
<Point X="435" Y="165" T="140" />
<Point X="436" Y="165" T="141" />
<Point X="437" Y="165" T="142" />
<Point X="438" Y="165" T="143" />
<Point X="439" Y="164" T="144" />
<Point X="440" Y="164" T="145" />
<Point X="441" Y="164" T="146" />
<Point X="442" Y="164" T="147" />
<Point X="443" Y="164" T="148" />
<Point X="444" Y="164" T="149" />
<Point X="444" Y="163" T="150" />
<Point X="444" Y="162" T="151" />
<Point X="444" Y="161" T="152" />
<Point X="444" Y="160" T="153" />
<Point X="445" Y="158" T="154" />
<Point X="445" Y="156" T="155" />
<Point X="446" Y="154" T="156" />
<Point X="446" Y="152" T="157" />
<Point X="446" Y="149" T="158" />
<Point X="446" Y="147" T="159" />
<Point X="447" Y="144" T="160" />
<Point X="447" Y="141" T="161" />
<Point X="447" Y="138" T="162" />
<Point X="447" Y="136" T="163" />
<Point X="448" Y="132" T="164" />
<Point X="448" Y="129" T="165" />
<Point X="448" Y="126" T="166" />
<Point X="448" Y="123" T="167" />
<Point X="448" Y="120" T="168" />
<Point X="449" Y="117" T="169" />
<Point X="449" Y="114" T="170" />
<Point X="449" Y="111" T="171" />
<Point X="449" Y="109" T="172" />
<Point X="450" Y="106" T="173" />
<Point X="450" Y="104" T="174" />
<Point X="450" Y="101" T="175" />
<Point X="450" Y="98" T="176" />
<Point X="451" Y="95" T="177" />
<Point X="451" Y="93" T="178" />
<Point X="451" Y="90" T="179" />
<Point X="452" Y="86" T="180" />
<Point X="452" Y="83" T="181" />
<Point X="452" Y="79" T="182" />
<Point X="452" Y="76" T="183" />
<Point X="453" Y="72" T="184" />
<Point X="453" Y="69" T="185" />
<Point X="453" Y="66" T="186" />
<Point X="453" Y="63" T="187" />
<Point X="453" Y="60" T="188" />
<Point X="453" Y="58" T="189" />
<Point X="453" Y="56" T="190" />
<Point X="453" Y="55" T="191" />
<Point X="453" Y="54" T="192" />
<Point X="452" Y="53" T="193" />
<Point X="452" Y="52" T="194" />
<Point X="452" Y="51" T="195" />
<Point X="452" Y="50" T="196" />
<Point X="451" Y="50" T="197" />
<Point X="450" Y="50" T="198" />
<Point X="449" Y="50" T="199" />
<Point X="448" Y="50" T="200" />
<Point X="447" Y="50" T="201" />
<Point X="446" Y="50" T="202" />
<Point X="445" Y="50" T="203" />
<Point X="444" Y="50" T="204" />
<Point X="443" Y="50" T="205" />
<Point X="441" Y="50" T="206" />
<Point X="440" Y="50" T="207" />
<Point X="438" Y="50" T="208" />
<Point X="436" Y="50" T="209" />
<Point X="434" Y="50" T="210" />
<Point X="432" Y="50" T="211" />
<Point X="430" Y="50" T="212" />
<Point X="427" Y="50" T="213" />
<Point X="425" Y="50" T="214" />
<Point X="422" Y="51" T="215" />
<Point X="420" Y="51" T="216" />
<Point X="417" Y="51" T="217" />
<Point X="414" Y="51" T="218" />
<Point X="412" Y="51" T="219" />
<Point X="409" Y="51" T="220" />
<Point X="406" Y="51" T="221" />
<Point X="403" Y="51" T="222" />
<Point X="400" Y="51" T="223" />
<Point X="397" Y="51" T="224" />
<Point X="394" Y="51" T="225" />
<Point X="390" Y="51" T="226" />
<Point X="387" Y="51" T="227" />
<Point X="383" Y="51" T="228" />
<Point X="380" Y="52" T="229" />
<Point X="376" Y="52" T="230" />
<Point X="372" Y="52" T="231" />
<Point X="368" Y="52" T="232" />
<Point X="364" Y="52" T="233" />
<Point X="360" Y="52" T="234" />
<Point X="356" Y="52" T="235" />
<Point X="352" Y="51" T="236" />
<Point X="348" Y="51" T="237" />
<Point X="344" Y="50" T="238" />
<Point X="340" Y="49" T="239" />
<Point X="336" Y="48" T="240" />
<Point X="333" Y="48" T="241" />
<Point X="329" Y="47" T="242" />
<Point X="325" Y="47" T="243" />
<Point X="322" Y="46" T="244" />
<Point X="318" Y="46" T="245" />
<Point X="315" Y="45" T="246" />
<Point X="312" Y="45" T="247" />
<Point X="309" Y="45" T="248" />
<Point X="306" Y="44" T="249" />
<Point X="303" Y="44" T="250" />
<Point X="301" Y="44" T="251" />
<Point X="298" Y="44" T="252" />
<Point X="295" Y="44" T="253" />
<Point X="293" Y="44" T="254" />
<Point X="290" Y="44" T="255" />
<Point X="287" Y="44" T="256" />
<Point X="285" Y="44" T="257" />
<Point X="282" Y="45" T="258" />
<Point X="279" Y="45" T="259" />
<Point X="276" Y="45" T="260" />
<Point X="274" Y="45" T="261" />
<Point X="271" Y="45" T="262" />
<Point X="269" Y="45" T="263" />
<Point X="267" Y="46" T="264" />
<Point X="265" Y="46" T="265" />
<Point X="263" Y="47" T="266" />
<Point X="261" Y="47" T="267" />
<Point X="259" Y="47" T="268" />
<Point X="258" Y="47" T="269" />
<Point X="256" Y="47" T="270" />
<Point X="254" Y="47" T="271" />
<Point X="253" Y="47" T="272" />
<Point X="252" Y="47" T="273" />
<Point X="250" Y="47" T="274" />
<Point X="249" Y="47" T="275" />
<Point X="248" Y="47" T="276" />
<Point X="247" Y="47" T="277" />
<Point X="246" Y="46" T="278" />
<Point X="245" Y="46" T="279" />
<Point X="243" Y="46" T="280" />
<Point X="242" Y="46" T="281" />
<Point X="240" Y="46" T="282" />
<Point X="238" Y="46" T="283" />
<Point X="237" Y="45" T="284" />
<Point X="235" Y="45" T="285" />
<Point X="233" Y="45" T="286" />
<Point X="231" Y="45" T="287" />
<Point X="229" Y="45" T="288" />
<Point X="227" Y="45" T="289" />
<Point X="225" Y="45" T="290" />
<Point X="223" Y="45" T="291" />
<Point X="222" Y="45" T="292" />
<Point X="220" Y="45" T="293" />
<Point X="219" Y="45" T="294" />
<Point X="217" Y="45" T="295" />
<Point X="216" Y="45" T="296" />
<Point X="215" Y="45" T="297" />
<Point X="214" Y="46" T="298" />
<Point X="213" Y="46" T="299" />
<Point X="212" Y="46" T="300" />
<Point X="211" Y="46" T="301" />
<Point X="210" Y="46" T="302" />
<Point X="209" Y="46" T="303" />
<Point X="208" Y="46" T="304" />
<Point X="207" Y="46" T="305" />
<Point X="206" Y="47" T="306" />
<Point X="205" Y="47" T="307" />
<Point X="204" Y="47" T="308" />
<Point X="203" Y="47" T="309" />
<Point X="201" Y="47" T="310" />
<Point X="200" Y="47" T="311" />
<Point X="199" Y="48" T="312" />
<Point X="198" Y="48" T="313" />
<Point X="196" Y="48" T="314" />
<Point X="195" Y="48" T="315" />
<Point X="194" Y="48" T="316" />
<Point X="193" Y="48" T="317" />
<Point X="192" Y="48" T="318" />
<Point X="191" Y="48" T="319" />
<Point X="190" Y="48" T="320" />
<Point X="189" Y="48" T="321" />
<Point X="188" Y="48" T="322" />
<Point X="187" Y="48" T="323" />
<Point X="186" Y="48" T="324" />
<Point X="185" Y="48" T="325" />
<Point X="184" Y="48" T="326" />
<Point X="183" Y="48" T="327" />
<Point X="182" Y="48" T="328" />
<Point X="181" Y="48" T="329" />
<Point X="179" Y="48" T="330" />
<Point X="178" Y="48" T="331" />
<Point X="176" Y="48" T="332" />
<Point X="175" Y="48" T="333" />
<Point X="173" Y="48" T="334" />
<Point X="171" Y="48" T="335" />
<Point X="170" Y="48" T="336" />
<Point X="168" Y="48" T="337" />
<Point X="167" Y="48" T="338" />
<Point X="166" Y="48" T="339" />
<Point X="164" Y="48" T="340" />
<Point X="163" Y="48" T="341" />
<Point X="162" Y="48" T="342" />
<Point X="161" Y="48" T="343" />
<Point X="160" Y="48" T="344" />
<Point X="159" Y="48" T="345" />
<Point X="158" Y="47" T="346" />
<Point X="157" Y="47" T="347" />
<Point X="156" Y="47" T="348" />
<Point X="155" Y="47" T="349" />
<Point X="154" Y="47" T="350" />
<Point X="153" Y="47" T="351" />
<Point X="152" Y="47" T="352" />
<Point X="151" Y="47" T="353" />
<Point X="150" Y="46" T="354" />
<Point X="149" Y="46" T="355" />
<Point X="148" Y="46" T="356" />
<Point X="147" Y="46" T="357" />
<Point X="146" Y="46" T="358" />
<Point X="145" Y="46" T="359" />
<Point X="144" Y="46" T="360" />
<Point X="143" Y="46" T="361" />
<Point X="142" Y="46" T="362" />
<Point X="141" Y="47" T="363" />
<Point X="140" Y="47" T="364" />
<Point X="139" Y="47" T="365" />
<Point X="138" Y="47" T="366" />
<Point X="137" Y="47" T="367" />
<Point X="137" Y="46" T="368" />
<Point X="136" Y="46" T="369" />
<Point X="135" Y="46" T="370" />
</Gesture>