<?xml version="1.0" encoding="utf-8" standalone="yes"?>
<Gesture Name="x4" Subject="user04" Number="4" NumPts="169">
   <Point X="271" Y="144" T="1677701530212" />
   <Point X="279" Y="154" T="1677701530213" />
   <Point X="281" Y="157" T="1677701530220" />
   <Point X="284" Y="159" T="1677701530229" />
   <Point X="287" Y="163" T="1677701530237" />
   <Point X="290" Y="167" T="1677701530244" />
   <Point X="294" Y="171" T="1677701530253" />
   <Point X="298" Y="176" T="1677701530260" />
   <Point X="304" Y="181" T="1677701530269" />
   <Point X="308" Y="186" T="1677701530276" />
   <Point X="314" Y="192" T="1677701530283" />
   <Point X="319" Y="197" T="1677701530291" />
   <Point X="324" Y="203" T="1677701530299" />
   <Point X="329" Y="209" T="1677701530302" />
   <Point X="335" Y="216" T="1677701530302" />
   <Point X="340" Y="221" T="1677701530317" />
   <Point X="345" Y="227" T="1677701530317" />
   <Point X="352" Y="233" T="1677701530333" />
   <Point X="356" Y="237" T="1677701530333" />
   <Point X="360" Y="243" T="1677701530348" />
   <Point X="364" Y="247" T="1677701530348" />
   <Point X="368" Y="251" T="1677701530364" />
   <Point X="373" Y="256" T="1677701530380" />
   <Point X="376" Y="261" T="1677701530380" />
   <Point X="379" Y="264" T="1677701530395" />
   <Point X="382" Y="267" T="1677701530405" />
   <Point X="385" Y="270" T="1677701530413" />
   <Point X="388" Y="273" T="1677701530420" />
   <Point X="390" Y="276" T="1677701530429" />
   <Point X="393" Y="279" T="1677701530434" />
   <Point X="395" Y="281" T="1677701530434" />
   <Point X="398" Y="285" T="1677701530450" />
   <Point X="400" Y="286" T="1677701530450" />
   <Point X="401" Y="288" T="1677701530465" />
   <Point X="402" Y="290" T="1677701530465" />
   <Point X="404" Y="291" T="1677701530481" />
   <Point X="406" Y="293" T="1677701530481" />
   <Point X="407" Y="296" T="1677701530497" />
   <Point X="409" Y="297" T="1677701530497" />
   <Point X="410" Y="299" T="1677701530512" />
   <Point X="412" Y="301" T="1677701530512" />
   <Point X="414" Y="303" T="1677701530528" />
   <Point X="415" Y="305" T="1677701530528" />
   <Point X="416" Y="307" T="1677701530544" />
   <Point X="418" Y="308" T="1677701530544" />
   <Point X="418" Y="309" T="1677701530559" />
   <Point X="419" Y="310" T="1677701530559" />
   <Point X="420" Y="311" T="1677701530579" />
   <Point X="420" Y="312" T="1677701530588" />
   <Point X="421" Y="313" T="1677701530595" />
   <Point X="422" Y="313" T="1677701530604" />
   <Point X="422" Y="314" T="1677701530628" />
   <Point X="422" Y="313" T="1677701530715" />
   <Point X="423" Y="313" T="1677701530723" />
   <Point X="423" Y="311" T="1677701530732" />
   <Point X="423" Y="310" T="1677701530740" />
   <Point X="423" Y="309" T="1677701530748" />
   <Point X="423" Y="307" T="1677701530755" />
   <Point X="423" Y="305" T="1677701530773" />
   <Point X="423" Y="304" T="1677701530780" />
   <Point X="423" Y="303" T="1677701530788" />
   <Point X="423" Y="301" T="1677701530805" />
   <Point X="423" Y="299" T="1677701530820" />
   <Point X="423" Y="297" T="1677701530828" />
   <Point X="423" Y="296" T="1677701530837" />
   <Point X="423" Y="294" T="1677701530844" />
   <Point X="423" Y="291" T="1677701530852" />
   <Point X="423" Y="289" T="1677701530860" />
   <Point X="423" Y="285" T="1677701530869" />
   <Point X="422" Y="279" T="1677701530876" />
   <Point X="421" Y="271" T="1677701530885" />
   <Point X="420" Y="265" T="1677701530893" />
   <Point X="419" Y="257" T="1677701530901" />
   <Point X="418" Y="251" T="1677701530909" />
   <Point X="418" Y="245" T="1677701530917" />
   <Point X="418" Y="239" T="1677701530925" />
   <Point X="418" Y="233" T="1677701530933" />
   <Point X="418" Y="226" T="1677701530940" />
   <Point X="419" Y="219" T="1677701530949" />
   <Point X="419" Y="211" T="1677701530957" />
   <Point X="419" Y="204" T="1677701530965" />
   <Point X="419" Y="197" T="1677701530973" />
   <Point X="419" Y="191" T="1677701530981" />
   <Point X="419" Y="185" T="1677701530989" />
   <Point X="419" Y="181" T="1677701530997" />
   <Point X="419" Y="177" T="1677701531005" />
   <Point X="419" Y="175" T="1677701531013" />
   <Point X="419" Y="171" T="1677701531021" />
   <Point X="419" Y="167" T="1677701531028" />
   <Point X="419" Y="165" T="1677701531036" />
   <Point X="419" Y="162" T="1677701531044" />
   <Point X="419" Y="160" T="1677701531052" />
   <Point X="419" Y="159" T="1677701531060" />
   <Point X="419" Y="157" T="1677701531068" />
   <Point X="419" Y="156" T="1677701531076" />
   <Point X="419" Y="155" T="1677701531085" />
   <Point X="419" Y="154" T="1677701531092" />
   <Point X="419" Y="153" T="1677701531100" />
   <Point X="419" Y="152" T="1677701531124" />
   <Point X="418" Y="152" T="1677701531278" />
   <Point X="417" Y="153" T="1677701531295" />
   <Point X="416" Y="153" T="1677701531303" />
   <Point X="415" Y="154" T="1677701531320" />
   <Point X="414" Y="155" T="1677701531326" />
   <Point X="413" Y="155" T="1677701531342" />
   <Point X="412" Y="156" T="1677701531349" />
   <Point X="412" Y="157" T="1677701531365" />
   <Point X="411" Y="157" T="1677701531374" />
   <Point X="410" Y="158" T="1677701531382" />
   <Point X="409" Y="159" T="1677701531389" />
   <Point X="408" Y="160" T="1677701531397" />
   <Point X="406" Y="161" T="1677701531406" />
   <Point X="404" Y="163" T="1677701531414" />
   <Point X="402" Y="165" T="1677701531422" />
   <Point X="399" Y="167" T="1677701531431" />
   <Point X="396" Y="170" T="1677701531434" />
   <Point X="394" Y="172" T="1677701531434" />
   <Point X="392" Y="173" T="1677701531454" />
   <Point X="390" Y="175" T="1677701531463" />
   <Point X="388" Y="177" T="1677701531470" />
   <Point X="386" Y="179" T="1677701531479" />
   <Point X="384" Y="181" T="1677701531485" />
   <Point X="381" Y="183" T="1677701531485" />
   <Point X="378" Y="186" T="1677701531501" />
   <Point X="375" Y="189" T="1677701531501" />
   <Point X="371" Y="192" T="1677701531517" />
   <Point X="366" Y="196" T="1677701531517" />
   <Point X="362" Y="199" T="1677701531532" />
   <Point X="359" Y="203" T="1677701531532" />
   <Point X="356" Y="205" T="1677701531548" />
   <Point X="352" Y="209" T="1677701531548" />
   <Point X="349" Y="212" T="1677701531563" />
   <Point X="345" Y="215" T="1677701531563" />
   <Point X="341" Y="219" T="1677701531579" />
   <Point X="338" Y="223" T="1677701531579" />
   <Point X="334" Y="226" T="1677701531595" />
   <Point X="331" Y="230" T="1677701531595" />
   <Point X="326" Y="235" T="1677701531610" />
   <Point X="322" Y="239" T="1677701531610" />
   <Point X="317" Y="243" T="1677701531626" />
   <Point X="314" Y="247" T="1677701531639" />
   <Point X="310" Y="251" T="1677701531647" />
   <Point X="306" Y="256" T="1677701531655" />
   <Point X="302" Y="259" T="1677701531663" />
   <Point X="298" Y="263" T="1677701531667" />
   <Point X="294" Y="266" T="1677701531667" />
   <Point X="292" Y="269" T="1677701531683" />
   <Point X="289" Y="272" T="1677701531683" />
   <Point X="287" Y="275" T="1677701531699" />
   <Point X="284" Y="278" T="1677701531699" />
   <Point X="281" Y="281" T="1677701531714" />
   <Point X="278" Y="283" T="1677701531714" />
   <Point X="276" Y="285" T="1677701531730" />
   <Point X="274" Y="287" T="1677701531730" />
   <Point X="272" Y="288" T="1677701531746" />
   <Point X="270" Y="289" T="1677701531746" />
   <Point X="269" Y="291" T="1677701531761" />
   <Point X="268" Y="291" T="1677701531761" />
   <Point X="266" Y="293" T="1677701531777" />
   <Point X="265" Y="293" T="1677701531777" />
   <Point X="264" Y="295" T="1677701531800" />
   <Point X="263" Y="295" T="1677701531806" />
   <Point X="262" Y="296" T="1677701531815" />
   <Point X="261" Y="297" T="1677701531824" />
   <Point X="260" Y="297" T="1677701531831" />
   <Point X="259" Y="298" T="1677701531834" />
   <Point X="259" Y="299" T="1677701531834" />
   <Point X="258" Y="299" T="1677701531850" />
   <Point X="258" Y="300" T="1677701531866" />
</Gesture>